auth_gate/__init__.py
auth_gate/config.py
auth_gate/exceptions.py
auth_gate/fastapi_utils.py
auth_gate/middleware.py
auth_gate/s2s_auth.py
auth_gate/schemas.py
auth_gate/subscription.py
auth_gate/user_auth.py
auth_gate-0.3.1.dist-info/licenses/LICENSE
tests/__init__.py
tests/conftest.py
tests/test_config.py
tests/test_fastapi_utils.py
tests/test_intergration.py
tests/test_middleware.py
tests/test_s2s_auth.py
tests/test_schema.py
tests/test_subscription.py
tests/test_user_auth.py
auth_gate-0.3.1.dist-info/METADATA
auth_gate-0.3.1.dist-info/WHEEL
auth_gate-0.3.1.dist-info/top_level.txt
auth_gate-0.3.1.dist-info/RECORD
