Metadata-Version: 2.4
Name: auth-gate
Version: 0.3.1
Summary: Enterprise-grade authentication for microservices with Kong/Keycloak integration and subscription tier support
Home-page: https://github.com/tradelink-org/auth-gate
Author: Brian Mburu
Author-email: Brian Mburu <brian.mburu@students.jkuat.ac.ke>
Maintainer-email: Brian Mburu <brian.mburu@students.jkuat.ac.ke>
License: MIT
Project-URL: Homepage, https://github.com/tradelink-org/auth-gate
Project-URL: Repository, https://github.com/tradelink-org/auth-gate.git
Project-URL: Documentation, https://github.com/tradelink-org/auth-gate.git
Project-URL: Bug Tracker, https://github.com/tradelink-org/auth-gate/issues
Keywords: authentication,keycloak,kong,fastapi,microservices
Classifier: Development Status :: 5 - Production/Stable
Classifier: Intended Audience :: Developers
Classifier: License :: OSI Approved :: MIT License
Classifier: Programming Language :: Python :: 3
Classifier: Programming Language :: Python :: 3.11
Classifier: Programming Language :: Python :: 3.12
Classifier: Topic :: Software Development :: Libraries :: Python Modules
Classifier: Topic :: Internet :: WWW/HTTP :: HTTP Servers
Classifier: Framework :: FastAPI
Requires-Python: >=3.11
License-File: LICENSE
Requires-Dist: fastapi>=0.109.0
Requires-Dist: pydantic>=2.5.0
Requires-Dist: pydantic-settings>=2.1.0
Requires-Dist: httpx>=0.26.0
Requires-Dist: python-jose[cryptography]>=3.3.0
Requires-Dist: starlette>=0.35.0
Provides-Extra: dev
Requires-Dist: pytest>=7.4.0; extra == "dev"
Requires-Dist: pytest-asyncio>=0.21.0; extra == "dev"
Requires-Dist: pytest-cov>=4.1.0; extra == "dev"
Requires-Dist: black>=23.0.0; extra == "dev"
Requires-Dist: mypy>=1.7.0; extra == "dev"
Requires-Dist: ruff>=0.1.0; extra == "dev"
Dynamic: license-file
